scikit_query-0.4.2.dist-info/licenses/LICENSE
skquery/__init__.py
skquery/exceptions.py
skquery/strategy.py
skquery/oracle/MLCLOracle.py
skquery/oracle/TripletOracle.py
skquery/oracle/__init__.py
skquery/pairwise/AIPC.py
skquery/pairwise/FFQS.py
skquery/pairwise/MinMax.py
skquery/pairwise/NPU.py
skquery/pairwise/Pairwise.py
skquery/pairwise/RandomMLCL.py
skquery/pairwise/SASC.py
skquery/pairwise/__init__.py
skquery/select/EntropySelection.py
skquery/select/NearestNeighborsSelection.py
skquery/select/RandomSelection.py
skquery/select/__init__.py
skquery/span_limited/RandomSpan.py
skquery/span_limited/__init__.py
skquery/tests/__init__.py
skquery/tests/conftest.py
skquery/tests/test_query_pw.py
skquery/tests/test_query_triplet.py
skquery/tests/test_selection.py
skquery/triplet/RandomTriplet.py
skquery/triplet/__init__.py
skquery/utils/BaseSVDD.py
skquery/utils/__init__.py
scikit_query-0.4.2.dist-info/METADATA
scikit_query-0.4.2.dist-info/WHEEL
scikit_query-0.4.2.dist-info/top_level.txt
scikit_query-0.4.2.dist-info/RECORD
