Metadata-Version: 2.4
Name: scikit-query
Version: 0.4.2
Summary: scikit-query is a Python library for active query strategies in constrained clustering on top of SciPy and scikit-learn.
Home-page: https://github.com/aymericb213/scikit-query
Author: Aymeric Beauchamp
Author-email: aymeric.beauchamp@univ-orleans.fr
License: BSD 3-Clause License
Keywords: active clustering,semi-supervised clustering,constrained clustering,pattern recognition,machine learning,artificial intelligence
Classifier: Intended Audience :: Science/Research
Classifier: Intended Audience :: Developers
Classifier: License :: OSI Approved :: BSD License
Classifier: Programming Language :: Python :: 3
Classifier: Programming Language :: Python :: 3.10
Classifier: Programming Language :: Python :: 3.11
Classifier: Operating System :: OS Independent
Requires-Python: >=3.10
License-File: LICENSE
Requires-Dist: active_semi_supervised_clustering>=0.0.1
Requires-Dist: clustering_benchmarks>=1.0.0
Requires-Dist: cvxopt<1.4
Requires-Dist: matplotlib<3.11
Requires-Dist: numpy<2.3
Requires-Dist: polars<1.28
Requires-Dist: setuptools<79.1
Requires-Dist: scikit_fuzzy
Requires-Dist: scikit_learn
Requires-Dist: scipy<1.16
Dynamic: author
Dynamic: author-email
Dynamic: classifier
Dynamic: description
Dynamic: description-content-type
Dynamic: home-page
Dynamic: keywords
Dynamic: license
Dynamic: license-file
Dynamic: requires-dist
Dynamic: requires-python
Dynamic: summary
